{
  "SpeechRecognitionAlternative": [
    {
      "transcript": " did needs",
      "confidence": 0.8626906871795654,
      "isFinal": true
    },
    {
      "transcript": "think of the European entities",
      "confidence": 0.8848811984062195,
      "isFinal": true
    },
    {
      "transcript": " did needs",
      "confidence": 0.8999999761581421,
      "isFinal": false
    },
    {
      "transcript": "think of the European entities",
      "confidence": 0.8848811984062195,
      "isFinal": true
    },
    {
      "transcript": " did needs",
      "confidence": 0.009999999776482582,
      "isFinal": false
    },
    {
      "transcript": "think of the European entities",
      "confidence": 0.8848811984062195,
      "isFinal": true
    },
    {
      "transcript": " and it needs to",
      "confidence": 0.009999999776482582,
      "isFinal": false
    },
    {
      "transcript": "think of the European entities",
      "confidence": 0.8848811984062195,
      "isFinal": true
    },
    {
      "transcript": " did needs",
      "confidence": 0.8999999761581421,
      "isFinal": false
    },
    {
      "transcript": "think of the European entities",
      "confidence": 0.8848811984062195,
      "isFinal": true
    },
    {
      "transcript": " did needs",
      "confidence": 0.009999999776482582,
      "isFinal": false
    },
    {
      "transcript": "think of the European entities",
      "confidence": 0.8848811984062195,
      "isFinal": true
    },
    {
      "transcript": " and it needs",
      "confidence": 0.009999999776482582,
      "isFinal": false
    },
    {
      "transcript": "think of the European entities",
      "confidence": 0.8848811984062195,
      "isFinal": true
    },
    {
      "transcript": "think of the European entities",
      "confidence": 0.8848811984062195,
      "isFinal": true
    },
    {
      "transcript": "think of the European countries",
      "confidence": 0.8999999761581421,
      "isFinal": false
    },
    {
      "transcript": " European countries",
      "confidence": 0.009999999776482582,
      "isFinal": false
    },
    {
      "transcript": "think of the",
      "confidence": 0.8999999761581421,
      "isFinal": false
    },
    {
      "transcript": "think of the uvula",
      "confidence": 0.8999999761581421,
      "isFinal": false
    },
    {
      "transcript": " uvula",
      "confidence": 0.009999999776482582,
      "isFinal": false
    },
    {
      "transcript": "think of the",
      "confidence": 0.8999999761581421,
      "isFinal": false
    },
    {
      "transcript": "think of the European",
      "confidence": 0.009999999776482582,
      "isFinal": false
    },
    {
      "transcript": "think of the year",
      "confidence": 0.009999999776482582,
      "isFinal": false
    },
    {
      "transcript": "thank God by",
      "confidence": 0.009999999776482582,
      "isFinal": false
    },
    {
      "transcript": "think of the",
      "confidence": 0.009999999776482582,
      "isFinal": false
    },
    {
      "transcript": "thank God",
      "confidence": 0.009999999776482582,
      "isFinal": false
    },
    {
      "transcript": "Lincoln",
      "confidence": 0.009999999776482582,
      "isFinal": false
    },
    {
      "transcript": "think",
      "confidence": 0.009999999776482582,
      "isFinal": false
    }
  ]
}